.DS_Store
text_sensitivity/.DS_Store
text_sensitivity/__init__.py
text_sensitivity/_version.py
text_sensitivity/internationalization.py
text_sensitivity/metrics.py
text_sensitivity/return_types.py
text_sensitivity/sensitivity.py
text_sensitivity/data/.DS_Store
text_sensitivity/data/__init__.py
text_sensitivity/data/base.py
text_sensitivity/data/generate.py
text_sensitivity/data/wordlist.py
text_sensitivity/data/lists/__init__.py
text_sensitivity/data/lists/cities_by_population_nl.csv
text_sensitivity/data/random/__init__.py
text_sensitivity/data/random/entity.py
text_sensitivity/data/random/string.py
text_sensitivity/perturbation/__init__.py
text_sensitivity/perturbation/base.py
text_sensitivity/perturbation/characters.py
text_sensitivity/perturbation/sentences.py
text_sensitivity/perturbation/words.py
text_sensitivity/test/data/test_wordlist.py
text_sensitivity/test/data/random/test_entity.py
text_sensitivity/test/data/random/test_string.py
text_sensitivity/test/perturbation/test_characters.py
text_sensitivity/test/perturbation/test_sentences.py
text_sensitivity/ui/__init__.py
text_sensitivity/ui/notebook.py
text_sensitivity-0.3.6.dist-info/licenses/LICENSE
text_sensitivity-0.3.6.dist-info/METADATA
text_sensitivity-0.3.6.dist-info/WHEEL
text_sensitivity-0.3.6.dist-info/top_level.txt
text_sensitivity-0.3.6.dist-info/RECORD
