Metadata-Version: 2.4
Name: text_sensitivity
Version: 0.3.6
Summary: Extension of text_explainability for sensitivity testing (robustness, fairness, safety)
Home-page: https://github.com/MarcelRobeer/text_sensitivity
Author: Marcel Robeer
Author-email: m.j.robeer@uu.nl
License: GNU LGPL v3
Classifier: Development Status :: 3 - Alpha
Classifier: Programming Language :: Python
Classifier: License :: OSI Approved :: GNU Lesser General Public License v3 or later (LGPLv3+)
Classifier: Topic :: Scientific/Engineering :: Artificial Intelligence
Requires-Python: >=3.8
License-File: LICENSE
Requires-Dist: genbase>=0.2.14
Requires-Dist: text-explainability>=0.6.5
Requires-Dist: nlpaug>=1.1.3
Requires-Dist: Faker>=9.2.0
Requires-Dist: yaspin>=0.15.0
Dynamic: author
Dynamic: author-email
Dynamic: classifier
Dynamic: description
Dynamic: description-content-type
Dynamic: home-page
Dynamic: license
Dynamic: license-file
Dynamic: requires-dist
Dynamic: requires-python
Dynamic: summary
